onchainpay_sdk/__init__.py
onchainpay_sdk/error.py
onchainpay_sdk/domains/__init__.py
onchainpay_sdk/domains/address_book/__init__.py
onchainpay_sdk/domains/advanced_account/__init__.py
onchainpay_sdk/domains/auto_swaps/__init__.py
onchainpay_sdk/domains/basic_actions/__init__.py
onchainpay_sdk/domains/blockchain_addresses/__init__.py
onchainpay_sdk/domains/crosschain_bridge/__init__.py
onchainpay_sdk/domains/crosschain_swaps/__init__.py
onchainpay_sdk/domains/invoices/__init__.py
onchainpay_sdk/domains/kyt/__init__.py
onchainpay_sdk/domains/orders/__init__.py
onchainpay_sdk/domains/orphan_transactions/__init__.py
onchainpay_sdk/domains/partners_api/__init__.py
onchainpay_sdk/domains/personal_addresses/__init__.py
onchainpay_sdk/domains/recurring_payments/__init__.py
onchainpay_sdk/domains/webhooks/__init__.py
onchainpay_sdk/domains/withdraws/__init__.py
onchainpay_sdk/resources/__init__.py
onchainpay_sdk/resources/constants.py
onchainpay_sdk/resources/requester.py
onchainpay_sdk/resources/utils.py
onchainpay_sdk-0.0.2.dist-info/LICENSE
onchainpay_sdk-0.0.2.dist-info/METADATA
onchainpay_sdk-0.0.2.dist-info/WHEEL
onchainpay_sdk-0.0.2.dist-info/top_level.txt
onchainpay_sdk-0.0.2.dist-info/RECORD
