Metadata-Version: 2.1
Name: onchainpay_sdk
Version: 0.0.2
Summary: SDK for onchainpay.io API
Home-page: https://github.com/onchainpay/onchainpay_sdk
Author: onchainpay.io Team
Author-email: hello@onchainpay.io
Project-URL: Bug Tracker, https://github.com/onchainpay/onchainpay_sdk/issues
Classifier: Programming Language :: Python :: 3
Classifier: License :: OSI Approved :: BSD License
Classifier: Operating System :: OS Independent
Requires-Python: >=3.6
License-File: LICENSE
Requires-Dist: requests >=2.28.0
